.mina/onebot-v11.toml
avilla/onebot/v11/__init__.py
avilla/onebot/v11/account.py
avilla/onebot/v11/capability.py
avilla/onebot/v11/collector/__init__.py
avilla/onebot/v11/collector/connection.py
avilla/onebot/v11/net/__init__.py
avilla/onebot/v11/net/base.py
avilla/onebot/v11/net/ws_client.py
avilla/onebot/v11/net/ws_server.py
avilla/onebot/v11/perform/__init__.py
avilla/onebot/v11/perform/action/__init__.py
avilla/onebot/v11/perform/action/admin.py
avilla/onebot/v11/perform/action/file.py
avilla/onebot/v11/perform/action/message.py
avilla/onebot/v11/perform/action/mute.py
avilla/onebot/v11/perform/action/request.py
avilla/onebot/v11/perform/action/scene.py
avilla/onebot/v11/perform/context.py
avilla/onebot/v11/perform/event/__init__.py
avilla/onebot/v11/perform/event/lifespan.py
avilla/onebot/v11/perform/event/message.py
avilla/onebot/v11/perform/event/notice.py
avilla/onebot/v11/perform/event/request.py
avilla/onebot/v11/perform/message/deserialize.py
avilla/onebot/v11/perform/message/serialize.py
avilla/onebot/v11/perform/query/__init__.py
avilla/onebot/v11/perform/query/file.py
avilla/onebot/v11/perform/query/friend.py
avilla/onebot/v11/perform/query/group.py
avilla/onebot/v11/perform/resource_fetch.py
avilla/onebot/v11/protocol.py
avilla/onebot/v11/resource.py
avilla/onebot/v11/service.py
avilla/onebot/v11/utils.py
avilla_onebot_v11-1.0.0a32.dist-info/METADATA
avilla_onebot_v11-1.0.0a32.dist-info/WHEEL
avilla_onebot_v11-1.0.0a32.dist-info/licenses/LICENSE
avilla_onebot_v11-1.0.0a32.dist-info/RECORD
