Metadata-Version: 2.1
Name: avilla-onebot-v11
Version: 1.0.0a32
Home-page: https://github.com/GraiaProject/Avilla
Author-Email: GreyElaina <GreyElaina@outlook.com>
License: MIT
Project-URL: Homepage, https://github.com/GraiaProject/Avilla
Project-URL: Repository, https://github.com/GraiaProject/Avilla
Requires-Python: >=3.9
Requires-Dist: aiohttp>=3.8.1
Requires-Dist: starlette>=0.34.0
Requires-Dist: wsproto>=1.2.0
Requires-Dist: avilla-core>=1.0.0a26
Requires-Dist: avilla-standard-qq>=1.0.0a22
Requires-Dist: graia-amnesia[asgi]>=0.9.0
